{
  "hero": {
    "title": "哔乐助播",
    "highlight": "让直播助播效率翻倍",
    "description": "专业级直播辅助工具 — 礼物自动上屏 · AI智能弹幕助手 · 智能录屏 · 特效仓库。你集中精力做直播，其他的让我来！",
    "primaryBtn": "立即下载新版",
    "primaryLink": "#downloads",
    "secondaryBtn": "了解功能",
    "secondaryLink": "#features"
  },
  "features": {
    "title": "✨ 核心能力",
    "list": [
      { "icon": "🎮", "title": "礼物自动上屏", "desc": "礼物条自动上屏，投喂后立即可见，牌面立即给足，情绪价值拉满。" },
      { "icon": "💬", "title": "AI智能弹幕助手", "desc": "AI自动欢迎、感谢大哥，智能提醒，不再冷场。" },
      { "icon": "📊", "title": "智能录屏", "desc": "礼物来了自动录屏，不再担心漏掉任何感动瞬间。" },
      { "icon": "🔧", "title": "特效仓库", "desc": "没有个性笼子，仓库里选，总有一款适合你。" }
    ]
  },
  "usage": {
    "title": "📖 使用说明",
    "steps": [
      { "num": 1, "title": "下载安装包", "desc": "从下方列表选择对应版本，点击「下载」获取安装程序。" },
      { "num": 2, "title": "运行安装", "desc": "双击 .exe 文件，按照指引完成安装。" },
      { "num": 3, "title": "登录/激活", "desc": "使用哔哩哔哩App扫码注册账号（注册免费），免费试用3天，推荐10人免费用半年。" },
      { "num": 4, "title": "助手登录", "desc": "使用哔哩哔哩App扫码登录助手账号，可随时切换。" },
      { "num": 5, "title": "连接直播间", "desc": "输入直播间房间号，进入直播间，畅享智能之旅。" }
    ],
    "faq": [
      { "q": "❓ 杀毒软件报毒怎么办？", "a": "本软件通过数字签名认证，如遇误报请添加信任区或临时关闭防护，安心使用。" },
      { "q": "❓ 如何更新到最新版？", "a": "软件内置自动更新提醒，确认后会自动覆盖安装。" },
      { "q": "❓ MD5 校验是什么？", "a": "用于验证文件完整性，下载后使用页面工具比对，防止文件损坏或被篡改。" }
    ]
  },
  "downloads": {
    "latestFirst": true,
    "packages": [
      {
        "version": "1.0.1",
        "fileName": "BileBile-1.0.1-win-x64.exe",
        "fileSize": "30.7 MB",
        "md5": "6B957949",
        "releaseDate": "2026-04-21",
        "changelog": "首次发布。",
        "downloadUrl": "https://bileassist.cn/bilebile/setup/BileBile-1.0.1-win-x64.exe?sign=abb7be658882ec30e7f048dfbc00fdad&t=1776757998",
        "isLatest": true
      }
    ]
  },
  "footer": {
    "copyright": "© 2026 哔乐传媒科技 | 专注直播生态"
  }
}